Workbook

Sheet Dashboard
A1: Sales Performance Dashboard — FY2025 (Sample Data)
A2: Pick a region in the yellow cell; KPIs, categories, and monthly trend update automatically.
A3: Select Region: | B3: All
A4: Filter criteria (helper) | B4: =IF(B3="All","*",B3) -> *
A5: KPI | B5: Value | E5: Region | F5: Revenue (INR) | G5: Share
A6: Total Revenue (INR) | B6: =SUMIFS('Sales Data'!$I$2:$I$241,'Sales Data'!$C$2:$C$241,$B$4) -> 18319638 | E6: North | F6: =SUMIFS('Sales Data'!$I$2:$I$241,'Sales Data'!$C$2:$C$241,E6) -> 4650775 | G6: =IFERROR(F6/$F$10,0) -> 0.25386829
A7: Total Orders | B7: =COUNTIFS('Sales Data'!$C$2:$C$241,$B$4) -> 240 | E7: South | F7: =SUMIFS('Sales Data'!$I$2:$I$241,'Sales Data'!$C$2:$C$241,E7) -> 5216350 | G7: =IFERROR(F7/$F$10,0) -> 0.2847409
A8: Avg Order Value (INR) | B8: =IFERROR(B6/B7,0) -> 76331.823 | E8: East | F8: =SUMIFS('Sales Data'!$I$2:$I$241,'Sales Data'!$C$2:$C$241,E8) -> 5114497.5 | G8: =IFERROR(F8/$F$10,0) -> 0.27918115
A9: Units Sold | B9: =SUMIFS('Sales Data'!$F$2:$F$241,'Sales Data'!$C$2:$C$241,$B$4) -> 1568 | E9: West | F9: =SUMIFS('Sales Data'!$I$2:$I$241,'Sales Data'!$C$2:$C$241,E9) -> 3338015 | G9: =IFERROR(F9/$F$10,0) -> 0.18220966
A10: Avg Discount Given | B10: =IFERROR(AVERAGEIFS('Sales Data'!$H$2:$H$241,'Sales Data'!$C$2:$C$241,$B$4),0) -> 0.0625 | E10: Total | F10: =SUM(F6:F9) -> 18319638 | G10: =SUM(G6:G9) -> 1
A11: Top Region (by revenue) | B11: =INDEX(E6:E9,MATCH(MAX(F6:F9),F6:F9,0)) -> South
A13: Monthly Revenue Trend (follows region filter) | E13: Revenue by Category (follows region filter)
A14: Month | B14: Revenue (INR) | C14: MoM Growth | E14: Category | F14: Revenue (INR) | G14: Share
A15: 45658 | B15: =SUMIFS('Sales Data'!$I$2:$I$241,'Sales Data'!$B$2:$B$241,">="&A15,'Sales Data'!$B$2:$B$241,"<"&EDATE(A15,1),'Sales Data'!$C$2:$C$241,$B$4) -> 1497560 | C15: n/a | E15: Electronics | F15: =SUMIFS('Sales Data'!$I$2:$I$241,'Sales Data'!$D$2:$D$241,E15,'Sales Data'!$C$2:$C$241,$B$4) -> 13446725 | G15: =IFERROR(F15/$F$19,0) -> 0.73400606
A16: 45689 | B16: =SUMIFS('Sales Data'!$I$2:$I$241,'Sales Data'!$B$2:$B$241,">="&A16,'Sales Data'!$B$2:$B$241,"<"&EDATE(A16,1),'Sales Data'!$C$2:$C$241,$B$4) -> 595925 | C16: =IFERROR(B16/B15-1,"n/a") -> -0.60206937 | E16: Furniture | F16: =SUMIFS('Sales Data'!$I$2:$I$241,'Sales Data'!$D$2:$D$241,E16,'Sales Data'!$C$2:$C$241,$B$4) -> 3608450 | G16: =IFERROR(F16/$F$19,0) -> 0.19697169
A17: 45717 | B17: =SUMIFS('Sales Data'!$I$2:$I$241,'Sales Data'!$B$2:$B$241,">="&A17,'Sales Data'!$B$2:$B$241,"<"&EDATE(A17,1),'Sales Data'!$C$2:$C$241,$B$4) -> 917255 | C17: =IFERROR(B17/B16-1,"n/a") -> 0.53921215 | E17: Office Supplies | F17: =SUMIFS('Sales Data'!$I$2:$I$241,'Sales Data'!$D$2:$D$241,E17,'Sales Data'!$C$2:$C$241,$B$4) -> 195637.5 | G17: =IFERROR(F17/$F$19,0) -> 0.010679114
A18: 45748 | B18: =SUMIFS('Sales Data'!$I$2:$I$241,'Sales Data'!$B$2:$B$241,">="&A18,'Sales Data'!$B$2:$B$241,"<"&EDATE(A18,1),'Sales Data'!$C$2:$C$241,$B$4) -> 1577480 | C18: =IFERROR(B18/B17-1,"n/a") -> 0.71978348 | E18: Accessories | F18: =SUMIFS('Sales Data'!$I$2:$I$241,'Sales Data'!$D$2:$D$241,E18,'Sales Data'!$C$2:$C$241,$B$4) -> 1068825 | G18: =IFERROR(F18/$F$19,0) -> 0.05834313
A19: 45778 | B19: =SUMIFS('Sales Data'!$I$2:$I$241,'Sales Data'!$B$2:$B$241,">="&A19,'Sales Data'!$B$2:$B$241,"<"&EDATE(A19,1),'Sales Data'!$C$2:$C$241,$B$4) -> 1726295 | C19: =IFERROR(B19/B18-1,"n/a") -> 0.094337171 | E19: Total | F19: =SUM(F15:F18) -> 18319638 | G19: =SUM(G15:G18) -> 1
A20: 45809 | B20: =SUMIFS('Sales Data'!$I$2:$I$241,'Sales Data'!$B$2:$B$241,">="&A20,'Sales Data'!$B$2:$B$241,"<"&EDATE(A20,1),'Sales Data'!$C$2:$C$241,$B$4) -> 812262.5 | C20: =IFERROR(B20/B19-1,"n/a") -> -0.52947642
A21: 45839 | B21: =SUMIFS('Sales Data'!$I$2:$I$241,'Sales Data'!$B$2:$B$241,">="&A21,'Sales Data'!$B$2:$B$241,"<"&EDATE(A21,1),'Sales Data'!$C$2:$C$241,$B$4) -> 2204630 | C21: =IFERROR(B21/B20-1,"n/a") -> 1.7141841
A22: 45870 | B22: =SUMIFS('Sales Data'!$I$2:$I$241,'Sales Data'!$B$2:$B$241,">="&A22,'Sales Data'!$B$2:$B$241,"<"&EDATE(A22,1),'Sales Data'!$C$2:$C$241,$B$4) -> 1183160 | C22: =IFERROR(B22/B21-1,"n/a") -> -0.46332945 | E22: Product Ranking (follows region filter)
A23: 45901 | B23: =SUMIFS('Sales Data'!$I$2:$I$241,'Sales Data'!$B$2:$B$241,">="&A23,'Sales Data'!$B$2:$B$241,"<"&EDATE(A23,1),'Sales Data'!$C$2:$C$241,$B$4) -> 1655427.5 | C23: =IFERROR(B23/B22-1,"n/a") -> 0.39915776 | E23: Product | F23: Revenue (INR) | G23: Rank
A24: 45931 | B24: =SUMIFS('Sales Data'!$I$2:$I$241,'Sales Data'!$B$2:$B$241,">="&A24,'Sales Data'!$B$2:$B$241,"<"&EDATE(A24,1),'Sales Data'!$C$2:$C$241,$B$4) -> 1458782.5 | C24: =IFERROR(B24/B23-1,"n/a") -> -0.11878805 | E24: Laptop | F24: =SUMIFS('Sales Data'!$I$2:$I$241,'Sales Data'!$E$2:$E$241,E24,'Sales Data'!$C$2:$C$241,$B$4) -> 8723000 | G24: =RANK(F24,$F$24:$F$33) -> 1
A25: 45962 | B25: =SUMIFS('Sales Data'!$I$2:$I$241,'Sales Data'!$B$2:$B$241,">="&A25,'Sales Data'!$B$2:$B$241,"<"&EDATE(A25,1),'Sales Data'!$C$2:$C$241,$B$4) -> 1797550 | C25: =IFERROR(B25/B24-1,"n/a") -> 0.23222619 | E25: Smartphone | F25: =SUMIFS('Sales Data'!$I$2:$I$241,'Sales Data'!$E$2:$E$241,E25,'Sales Data'!$C$2:$C$241,$B$4) -> 4210800 | G25: =RANK(F25,$F$24:$F$33) -> 2
A26: 45992 | B26: =SUMIFS('Sales Data'!$I$2:$I$241,'Sales Data'!$B$2:$B$241,">="&A26,'Sales Data'!$B$2:$B$241,"<"&EDATE(A26,1),'Sales Data'!$C$2:$C$241,$B$4) -> 2893310 | C26: =IFERROR(B26/B25-1,"n/a") -> 0.60958527 | E26: Headphones | F26: =SUMIFS('Sales Data'!$I$2:$I$241,'Sales Data'!$E$2:$E$241,E26,'Sales Data'!$C$2:$C$241,$B$4) -> 512925 | G26: =RANK(F26,$F$24:$F$33) -> 6
A27: Total | B27: =SUM(B15:B26) -> 18319638 | E27: Office Chair | F27: =SUMIFS('Sales Data'!$I$2:$I$241,'Sales Data'!$E$2:$E$241,E27,'Sales Data'!$C$2:$C$241,$B$4) -> 1034450 | G27: =RANK(F27,$F$24:$F$33) -> 4
E28: Standing Desk | F28: =SUMIFS('Sales Data'!$I$2:$I$241,'Sales Data'!$E$2:$E$241,E28,'Sales Data'!$C$2:$C$241,$B$4) -> 2574000 | G28: =RANK(F28,$F$24:$F$33) -> 3
E29: Printer Paper (Box) | F29: =SUMIFS('Sales Data'!$I$2:$I$241,'Sales Data'!$E$2:$E$241,E29,'Sales Data'!$C$2:$C$241,$B$4) -> 163260 | G29: =RANK(F29,$F$24:$F$33) -> 9
E30: Notebook Pack | F30: =SUMIFS('Sales Data'!$I$2:$I$241,'Sales Data'!$E$2:$E$241,E30,'Sales Data'!$C$2:$C$241,$B$4) -> 32377.5 | G30: =RANK(F30,$F$24:$F$33) -> 10
E31: Keyboard | F31: =SUMIFS('Sales Data'!$I$2:$I$241,'Sales Data'!$E$2:$E$241,E31,'Sales Data'!$C$2:$C$241,$B$4) -> 336160 | G31: =RANK(F31,$F$24:$F$33) -> 7
E32: Mouse | F32: =SUMIFS('Sales Data'!$I$2:$I$241,'Sales Data'!$E$2:$E$241,E32,'Sales Data'!$C$2:$C$241,$B$4) -> 169785 | G32: =RANK(F32,$F$24:$F$33) -> 8
E33: Webcam | F33: =SUMIFS('Sales Data'!$I$2:$I$241,'Sales Data'!$E$2:$E$241,E33,'Sales Data'!$C$2:$C$241,$B$4) -> 562880 | G33: =RANK(F33,$F$24:$F$33) -> 5
E34: Top product | F34: =INDEX(E24:E33,MATCH(1,G24:G33,0)) -> Laptop

Sheet Sales Data
A1: Order ID | B1: Date | C1: Region | D1: Category | E1: Product | F1: Units | G1: Unit Price (INR) | H1: Discount % | I1: Revenue (INR)
A2: ORD-1001 | B2: 45658 | C2: West | D2: Accessories | E2: Webcam | F2: 2 | G2: 3200 | H2: 0.1 | I2: =F2*G2*(1-H2) -> 5760
A3: ORD-1002 | B3: 45660 | C3: West | D3: Furniture | E3: Standing Desk | F3: 6 | G3: 18000 | H3: 0 | I3: =F3*G3*(1-H3) -> 108000
A4: ORD-1003 | B4: 45661 | C4: West | D4: Accessories | E4: Mouse | F4: 9 | G4: 900 | H4: 0.15 | I4: =F4*G4*(1-H4) -> 6885
A5: ORD-1004 | B5: 45662 | C5: North | D5: Office Supplies | E5: Printer Paper (Box) | F5: 5 | G5: 1200 | H5: 0.05 | I5: =F5*G5*(1-H5) -> 5700
A6: ORD-1005 | B6: 45663 | C6: South | D6: Electronics | E6: Laptop | F6: 9 | G6: 55000 | H6: 0.05 | I6: =F6*G6*(1-H6) -> 470250
A7: ORD-1006 | B7: 45663 | C7: East | D7: Accessories | E7: Mouse | F7: 6 | G7: 900 | H7: 0 | I7: =F7*G7*(1-H7) -> 5400
A8: ORD-1007 | B8: 45667 | C8: East | D8: Furniture | E8: Office Chair | F8: 7 | G8: 8500 | H8: 0.1 | I8: =F8*G8*(1-H8) -> 53550
A9: ORD-1008 | B9: 45667 | C9: West | D9: Furniture | E9: Office Chair | F9: 3 | G9: 8500 | H9: 0.05 | I9: =F9*G9*(1-H9) -> 24225
A10: ORD-1009 | B10: 45669 | C10: South | D10: Electronics | E10: Headphones | F10: 2 | G10: 3500 | H10: 0.1 | I10: =F10*G10*(1-H10) -> 6300
A11: ORD-1010 | B11: 45669 | C11: West | D11: Electronics | E11: Smartphone | F11: 6 | G11: 24000 | H11: 0 | I11: =F11*G11*(1-H11) -> 144000
A12: ORD-1011 | B12: 45671 | C12: South | D12: Electronics | E12: Smartphone | F12: 8 | G12: 24000 | H12: 0 | I12: =F12*G12*(1-H12) -> 192000
A13: ORD-1012 | B13: 45671 | C13: North | D13: Office Supplies | E13: Printer Paper (Box) | F13: 11 | G13: 1200 | H13: 0.05 | I13: =F13*G13*(1-H13) -> 12540
... A241: ORD-1240 | B241: 46019 | C241: East | D241: Office Supplies | E241: Printer Paper (Box) | F241: 1 | G241: 1200 | H241: 0.05 | I241: =F241*G241*(1-H241) -> 1140

Sheet Notes
A1: About this workbook
A2: Purpose: interactive sales dashboard built to demonstrate Advanced Excel reporting skills.
A3: Data: 240 SAMPLE orders (Jan–Dec 2025) generated for demonstration. Not real company data.
A5: How to use
A6: 1. Open the Dashboard sheet and change the yellow cell (B3) to filter by region.
A7: 2. Edit Units, Unit Price or Discount % (blue font) on Sales Data; Revenue and every dashboard figure recalculate.
A9: Excel features used
A10: SUMIFS / COUNTIFS / AVERAGEIFS with wildcard criteria for the "All" option
A11: INDEX-MATCH to find the top region and top product; RANK for product ranking
A12: EDATE + date-range SUMIFS for the monthly trend; month-over-month growth formulas
A13: Data Validation dropdown, Conditional Formatting (data bars, colour scale, +/- highlighting)
A14: Bar and line charts linked to the summary tables; frozen header row and AutoFilter on the data sheet
... A17: Revenue = Units x Unit Price x (1 - Discount %). Currency is INR. Blue font = hardcoded inputs, black = formulas.
